ab_core/alembic_auto_migrate/__init__.py
ab_core/alembic_auto_migrate/service.py
ab_alembic_auto_migrate-0.2.1.dist-info/METADATA
ab_alembic_auto_migrate-0.2.1.dist-info/WHEEL
ab_alembic_auto_migrate-0.2.1.dist-info/licenses/LICENSE
ab_alembic_auto_migrate-0.2.1.dist-info/RECORD
