Metadata-Version: 2.4
Name: ab-alembic-auto-migrate
Version: 0.2.1
Summary: Auto migration using alembic.
Author-email: Matt Coulter <mattcoul7@gmail.com>
License-File: LICENSE
Requires-Python: <4.0,>=3.12
Requires-Dist: alembic>=1.16.5
Requires-Dist: pydantic<3,>=2.11.7
Requires-Dist: sqlmodel<0.0.25,>=0.0.24
